odoo/addons/maintenance_request_sequence/README.rst
odoo/addons/maintenance_request_sequence/__init__.py
odoo/addons/maintenance_request_sequence/__manifest__.py
odoo/addons/maintenance_request_sequence/data/maintenance_request_data.xml
odoo/addons/maintenance_request_sequence/i18n/es.po
odoo/addons/maintenance_request_sequence/i18n/it.po
odoo/addons/maintenance_request_sequence/i18n/maintenance_request_sequence.pot
odoo/addons/maintenance_request_sequence/i18n/pt_BR.po
odoo/addons/maintenance_request_sequence/models/__init__.py
odoo/addons/maintenance_request_sequence/models/maintenance_request.py
odoo/addons/maintenance_request_sequence/models/maintenance_team.py
odoo/addons/maintenance_request_sequence/readme/CONTRIBUTORS.rst
odoo/addons/maintenance_request_sequence/readme/DESCRIPTION.rst
odoo/addons/maintenance_request_sequence/static/description/icon.png
odoo/addons/maintenance_request_sequence/static/description/index.html
odoo/addons/maintenance_request_sequence/tests/__init__.py
odoo/addons/maintenance_request_sequence/tests/test_maintenance_request_sequence.py
odoo/addons/maintenance_request_sequence/views/maintenance_request.xml
odoo/addons/maintenance_request_sequence/views/maintenance_team.xml
odoo13_addon_maintenance_request_sequence-13.0.1.0.1.dev6.dist-info/METADATA
odoo13_addon_maintenance_request_sequence-13.0.1.0.1.dev6.dist-info/WHEEL
odoo13_addon_maintenance_request_sequence-13.0.1.0.1.dev6.dist-info/top_level.txt
odoo13_addon_maintenance_request_sequence-13.0.1.0.1.dev6.dist-info/RECORD
